{
  "date": "2026-05-01",
  "body": "Digital assets posted modest gains across the board on Thursday, with the total crypto market cap climbing 1.29% to $2.66T as buyers stepped in during Asian trading hours. The session's $74.1B in volume remained subdued compared to recent weeks, but the broad-based advance suggests institutional flows are finding their way back into risk assets despite lingering macro headwinds. Fear and Greed dropped to 26 from yesterday's 29, indicating retail sentiment remains cautious even as prices drift higher. Bitcoin's 58.3% dominance held steady while most major tokens participated in the rally, signaling some semblance of risk-on behavior returning to crypto markets.\n\nBitcoin pushed through $77,333, up 1.72% on the day and leading the charge higher as shorts faced pressure from the sustained move above $75,000. The king coin's $30.87B trading volume was the heaviest among all digital assets, with CryptoQuant noting that April's rally was primarily futures-driven rather than spot-led, which could limit the sustainability of further gains. Key resistance sits at $78,500, where previous rallies have stalled, while support has firmed around $74,000. The weekly chart shows BTC down just 0.63% over 7 days, suggesting consolidation rather than a meaningful correction as the market digests recent gains.\n\nEthereum gained 1.25% to $2,284.34, maintaining its correlation with Bitcoin while posting its own solid performance on $10.95B volume. Solana matched ETH's pace with a 1.26% advance to $84.15, continuing to outperform most large-caps on a relative basis. Notable divergences emerged in the mid-cap space, with Avalanche slipping 0.23% to $9.13 and Polkadot down 0.22% to $1.21, suggesting some rotation within altcoin rankings. XRP managed only a 0.39% gain despite the broader rally, while Cardano's 1.15% jump to $0.25 stood out among proof-of-stake tokens.\n\nThe macro backdrop remains mixed as markets digest earnings season and await clarity on Federal Reserve policy direction. Senator Warren's questioning of Commerce Secretary Lutnick on Tether lending practices adds another regulatory overhang, while the U.S. Senate's self-imposed ban on prediction market betting removes one potential catalyst for crypto adoption. Bithumb's legal victory in South Korea provides some positive regulatory news from Asia, but institutional players like Cathie Wood and Cantor Fitzgerald betting on Robinhood's crypto recovery suggests Wall Street views current weakness as temporary rather than structural.\n\nNext week brings several key catalysts that could shift market dynamics significantly. The monthly jobs report on Friday will influence Fed expectations, while ongoing earnings from tech giants could either support or undermine risk asset sentiment. Watch for any follow-up on the Warren-Lutnick Tether situation, as regulatory pressure on stablecoins has historically triggered sharp selloffs. On the technical side, Bitcoin needs to hold $75,000 on any pullbacks to maintain bullish momentum, while a break above $78,500 would likely trigger algorithmic buying and push the next leg higher toward $80,000.",
  "btc_price": 77333,
  "fg_value": "26",
  "fg_label": "Fear"
}